LICENSE.txt
MANIFEST.in
README.md
setup.py
../../SQL/ExecSQL_compare/compare/md_compare.sql
../../SQL/ExecSQL_compare/compare/pg_compare.sql
../../SQL/ExecSQL_compare/compare/ss_compare.sql
../../SQL/ExecSQL_glossary/glossary/md_glossary.sql
../../SQL/ExecSQL_glossary/glossary/pg_glossary.sql
../../SQL/ExecSQL_glossary/glossary/ss_glossary.sql
../../SQL/ExecSQL_upsert/upsert/md_upsert.sql
../../SQL/ExecSQL_upsert/upsert/pg_upsert.sql
../../SQL/ExecSQL_upsert/upsert/ss_upsert.sql
execsql/execsql.py
execsql.egg-info/PKG-INFO
execsql.egg-info/SOURCES.txt
execsql.egg-info/dependency_links.txt
execsql.egg-info/top_level.txt
templates/READ_ME.rst
templates/config_settings.sqlite
templates/example_config_prompt.sql
templates/execsql.conf
templates/md_compare.sql
templates/md_glossary.sql
templates/md_upsert.sql
templates/pg_compare.sql
templates/pg_glossary.sql
templates/pg_upsert.sql
templates/script_template.sql
templates/ss_compare.sql
templates/ss_glossary.sql
templates/ss_upsert.sql