Metadata-Version: 2.1
Name: execsql
Version: 1.130.1
Summary: Runs a SQL script against a PostgreSQL, SQLite, MariaDB/MySQL, DuckDB, Firebird, MS-Access, MS-SQL-Server, or Oracle database, or an ODBC DSN.  Provides metacommands to import and export data, copy data between databases, conditionally execute SQL and metacommands, and dynamically alter SQL and metacommands with substitution variables.  Data can be exported in 18 different formats, including CSV, TSV, ODS, HTML, JSON, LaTeX, and Markdown tables, and using custom templates.
Home-page: https://osdn.net/project/execsql/
Author: Dreas Nielsen
Author-email: cortice@tutanota.com
License: GPL
Keywords: SQL,Postgres,PostgreSQL,SQLite,Firebird,Access,SQL Server,MySQL,MariaDb,ODBC,Oracle,DuckDB,database,xlrd,psycopg2,pyodbc,pymysql,fdb,cx_Oracle,cx-Oracle,odfpy,ETL,CSV,TSV,XML,HTML,JSON,Feather,LaTeX,OpenDocument,table,DBMS,Redshift,CockroachDB,query,script,import,export,Parquet,template,Jinja,Airspeed,zip
Classifier: Development Status :: 5 - Production/Stable
Classifier: Environment :: Console
Classifier: Environment :: X11 Applications
Classifier: Environment :: Win32 (MS Windows)
Classifier: Intended Audience :: End Users/Desktop
Classifier: Intended Audience :: Information Technology
Classifier: Intended Audience :: System Administrators
Classifier: License :: OSI Approved :: GNU General Public License (GPL)
Classifier: Natural Language :: English
Classifier: Operating System :: OS Independent
Classifier: Operating System :: POSIX
Classifier: Operating System :: Microsoft :: Windows
Classifier: Programming Language :: Python :: 2
Classifier: Programming Language :: Python :: 3
Classifier: Programming Language :: Python :: 2.7
Classifier: Topic :: Database
Classifier: Topic :: Database :: Front-Ends
Classifier: Topic :: Office/Business
Classifier: Topic :: Scientific/Engineering
Requires-Python: >=2.7
License-File: LICENSE.txt
